strix_sandbox/__init__.py
strix_sandbox/prompts.py
strix_sandbox/server.py
strix_sandbox/runtime/__init__.py
strix_sandbox/runtime/docker.py
strix_sandbox/runtime/state.py
strix_sandbox/tools/__init__.py
strix_sandbox/tools/browser.py
strix_sandbox/tools/files.py
strix_sandbox/tools/findings.py
strix_sandbox/tools/proxy.py
strix_sandbox/tools/python_exec.py
strix_sandbox/tools/sandbox.py
strix_sandbox/tools/terminal.py
strix_sandbox/tools/agents/__init__.py
strix_sandbox/tools/agents/message_bus.py
strix_sandbox/tools/agents/models.py
strix_sandbox/tools/agents/state_store.py
strix_sandbox/tools/agents/tools.py
strix_sandbox/utils/__init__.py
strix_sandbox/utils/helpers.py
strix_sandbox-0.2.0.dist-info/METADATA
strix_sandbox-0.2.0.dist-info/WHEEL
strix_sandbox-0.2.0.dist-info/entry_points.txt
strix_sandbox-0.2.0.dist-info/RECORD
