Metadata-Version: 2.4
Name: strix-sandbox
Version: 0.2.0
Summary: Sandboxed security testing MCP server for Claude Code
Project-URL: Homepage, https://github.com/usestrix/strix
Project-URL: Repository, https://github.com/usestrix/strix
Project-URL: Documentation, https://github.com/usestrix/strix#readme
Project-URL: Bug Tracker, https://github.com/usestrix/strix/issues
Project-URL: Changelog, https://github.com/usestrix/strix/blob/main/mcp-server/CHANGELOG.md
Author-email: Strix <security@strix.dev>
License: MIT
Keywords: claude,mcp,penetration-testing,sandbox,security,testing,vulnerability-scanner
Classifier: Development Status :: 4 - Beta
Classifier: Intended Audience :: Developers
Classifier: Intended Audience :: Information Technology
Classifier: License :: OSI Approved :: MIT License
Classifier: Operating System :: OS Independent
Classifier: Programming Language :: Python :: 3
Classifier: Programming Language :: Python :: 3.11
Classifier: Programming Language :: Python :: 3.12
Classifier: Topic :: Security
Classifier: Topic :: Software Development :: Quality Assurance
Classifier: Topic :: Software Development :: Testing
Classifier: Typing :: Typed
Requires-Python: >=3.11
Requires-Dist: aiosqlite>=0.19.0
Requires-Dist: docker>=7.0.0
Requires-Dist: fastapi>=0.109.0
Requires-Dist: httpx>=0.26.0
Requires-Dist: mcp>=1.0.0
Requires-Dist: pydantic>=2.5.0
Requires-Dist: uvicorn>=0.27.0
Provides-Extra: dev
Requires-Dist: mypy>=1.8.0; extra == 'dev'
Requires-Dist: pytest-asyncio>=0.23.0; extra == 'dev'
Requires-Dist: pytest-cov>=4.0.0; extra == 'dev'
Requires-Dist: pytest>=8.0.0; extra == 'dev'
Requires-Dist: ruff>=0.1.0; extra == 'dev'
